process_formula/__init__.py
process_formula/normalize_formulas.py
process_formula/preprocess_latex.js
process_formula/third_party/katex/LICENSE.txt
process_formula/third_party/katex/README.md
process_formula/third_party/katex/cli.js
process_formula/third_party/katex/katex.js
process_formula/third_party/katex/package.json
process_formula/third_party/katex/src/Lexer.js
process_formula/third_party/katex/src/Options.js
process_formula/third_party/katex/src/ParseError.js
process_formula/third_party/katex/src/Parser.js
process_formula/third_party/katex/src/Settings.js
process_formula/third_party/katex/src/Style.js
process_formula/third_party/katex/src/buildCommon.js
process_formula/third_party/katex/src/buildHTML.js
process_formula/third_party/katex/src/buildMathML.js
process_formula/third_party/katex/src/buildTree.js
process_formula/third_party/katex/src/delimiter.js
process_formula/third_party/katex/src/domTree.js
process_formula/third_party/katex/src/environments.js
process_formula/third_party/katex/src/fontMetrics.js
process_formula/third_party/katex/src/fontMetricsData.js
process_formula/third_party/katex/src/functions.js
process_formula/third_party/katex/src/mathMLTree.js
process_formula/third_party/katex/src/parseData.js
process_formula/third_party/katex/src/parseTree.js
process_formula/third_party/katex/src/symbols.js
process_formula/third_party/katex/src/utils.js
process_formula/third_party/match-at/package.json
process_formula/third_party/match-at/lib/matchAt.js
process_formula-0.0.4.dist-info/LICENSE
process_formula-0.0.4.dist-info/METADATA
process_formula-0.0.4.dist-info/WHEEL
process_formula-0.0.4.dist-info/entry_points.txt
process_formula-0.0.4.dist-info/top_level.txt
process_formula-0.0.4.dist-info/RECORD
